fuckcaptcha.py
fuckcaptcha_data/__init__.py
fuckcaptcha_data/fuck.js
fuckcaptcha-0.1.0.dist-info/METADATA
fuckcaptcha-0.1.0.dist-info/WHEEL
fuckcaptcha-0.1.0.dist-info/top_level.txt
fuckcaptcha-0.1.0.dist-info/RECORD
