Metadata-Version: 2.1
Name: fuckcaptcha
Version: 0.1.0
Summary: bypass reCAPTCHA detection in pyppeteer
Home-page: https://github.com/Francesco149/fuckcaptcha
Author: Franc[e]sco
Author-email: lolisamurai@tfwno.gf
License: Unlicense
Keywords: stealth recaptcha captcha chrome chromium headless bypass
Platform: UNKNOWN
Classifier: Intended Audience :: Developers
Classifier: License :: Public Domain
Classifier: Topic :: Software Development :: Libraries
